rsa_scheduler_components
