Metadata-Version: 1.1
Name: rsa-scheduler-components
Version: 0.1.8
Summary: Schedule components for the RSA Scheduler app.
Home-page: UNKNOWN
Author: Ali Mojadam <amojadam@ashleyfurniture.com>
Author-email: UNKNOWN
License: MIT
Platform: UNKNOWN
Classifier: Framework :: Dash
